agent_engine_cli/__init__.py
agent_engine_cli/chat.py
agent_engine_cli/client.py
agent_engine_cli/config.py
agent_engine_cli/main.py
agent_engine_cli-0.1.3.dist-info/METADATA
agent_engine_cli-0.1.3.dist-info/WHEEL
agent_engine_cli-0.1.3.dist-info/entry_points.txt
agent_engine_cli-0.1.3.dist-info/licenses/LICENSE
agent_engine_cli-0.1.3.dist-info/RECORD
