Metadata-Version: 2.4
Name: agent-engine-cli
Version: 0.1.3
Summary: Command-line interface for managing Google Cloud Vertex AI Agent Engine deployments
Project-URL: Homepage, https://github.com/mmontan/agent-engine-cli
Project-URL: Bug Tracker, https://github.com/mmontan/agent-engine-cli/issues
Author: Mirko Montanari
License-Expression: MIT
License-File: LICENSE
Keywords: agent,agent-engine,agents,ai,automation,cli,gcp,google-cloud,llm,vertex,vertex-ai
Classifier: Development Status :: 4 - Beta
Classifier: Environment :: Console
Classifier: Intended Audience :: Developers
Classifier: License :: OSI Approved :: MIT License
Classifier: Operating System :: OS Independent
Classifier: Programming Language :: Python :: 3
Classifier: Programming Language :: Python :: 3.10
Classifier: Programming Language :: Python :: 3.11
Classifier: Programming Language :: Python :: 3.12
Classifier: Programming Language :: Python :: 3.13
Classifier: Topic :: Software Development :: Libraries :: Python Modules
Classifier: Topic :: Utilities
Requires-Python: >=3.10
Requires-Dist: google-cloud-aiplatform>=1.133.0
Requires-Dist: requests>=2.31.0
Requires-Dist: typer>=0.9.0
